cvxpy_tinoco/arrays.py
cvxpy_tinoco/constraints.py
cvxpy_tinoco/defs.py
cvxpy_tinoco/interface.py
cvxpy_tinoco/programs.py
cvxpy_tinoco/scalars.py
cvxpy_tinoco/utils.py
cvxpy_tinoco/__init__.py
cvxpy_tinoco/functions/abs.py
cvxpy_tinoco/functions/det_rootn.py
cvxpy_tinoco/functions/exp.py
cvxpy_tinoco/functions/geo_mean.py
cvxpy_tinoco/functions/huber.py
cvxpy_tinoco/functions/kl_div.py
cvxpy_tinoco/functions/lambda_max.py
cvxpy_tinoco/functions/lambda_min.py
cvxpy_tinoco/functions/log.py
cvxpy_tinoco/functions/log_norm_cdf.py
cvxpy_tinoco/functions/log_sum_exp.py
cvxpy_tinoco/functions/max.py
cvxpy_tinoco/functions/min.py
cvxpy_tinoco/functions/norm1.py
cvxpy_tinoco/functions/norm2.py
cvxpy_tinoco/functions/norm_inf.py
cvxpy_tinoco/functions/nuclear_norm.py
cvxpy_tinoco/functions/power_abs.py
cvxpy_tinoco/functions/power_p.py
cvxpy_tinoco/functions/power_pos.py
cvxpy_tinoco/functions/quad_form.py
cvxpy_tinoco/functions/quad_over_lin.py
cvxpy_tinoco/functions/sqrt.py
cvxpy_tinoco/functions/square.py
cvxpy_tinoco/functions/__init__.py
cvxpy_tinoco/procedures/call_solver.py
cvxpy_tinoco/procedures/expand.py
cvxpy_tinoco/procedures/re_eval.py
cvxpy_tinoco/procedures/solve_prog.py
cvxpy_tinoco/procedures/__init__.py
cvxpy_tinoco/sets/exp_cone.py
cvxpy_tinoco/sets/geo_mean_cone.py
cvxpy_tinoco/sets/kl_div_epi.py
cvxpy_tinoco/sets/log_norm_cdf_hypo.py
cvxpy_tinoco/sets/power_pos_epi.py
cvxpy_tinoco/sets/second_order_cone.py
cvxpy_tinoco/sets/semidefinite_cone.py
cvxpy_tinoco/sets/__init__.py
pydsm/audio_weightings.py
pydsm/correlations.py
pydsm/exceptions.py
pydsm/ft.py
pydsm/ir.py
pydsm/iso226.py
pydsm/relab.py
pydsm/RELEASE-VERSION
pydsm/simulation.py
pydsm/utilities.py
pydsm/_version.py
pydsm/__init__.py
pydsm/delsig/_axisLabels.py
pydsm/delsig/_clans.py
pydsm/delsig/_decibel.py
pydsm/delsig/_ds.py
pydsm/delsig/_dsclansNTF.py
pydsm/delsig/_padding.py
pydsm/delsig/_partitionABCD.py
pydsm/delsig/_plot.py
pydsm-0.13.0.1.dist-info/DESCRIPTION.rst
pydsm-0.13.0.1.dist-info/METADATA
pydsm-0.13.0.1.dist-info/metadata.json
pydsm-0.13.0.1.dist-info/pbr.json
pydsm-0.13.0.1.dist-info/RECORD
pydsm-0.13.0.1.dist-info/top_level.txt
pydsm-0.13.0.1.dist-info/WHEEL
