Metadata-Version: 2.0
Name: pydsm
Version: 0.13.0.1
Summary: Python Based Delta-Sigma modulator design tools
Home-page: https://github.com/sergiocallegari/PyDSM
Author: Sergio Callegari
Author-email: sergio.callegari@unibo.it
License: GNU General Public License v3 or later (GPLv3+)
Platform: Linux
Platform: Windows
Platform: Mac
Classifier: Development Status :: 4 - Beta
Classifier: Environment :: Console
Classifier: Intended Audience :: Education
Classifier: Intended Audience :: Science/Research
Classifier: Intended Audience :: Developers
Classifier: License :: OSI Approved :: GNU General Public License v3 or later (GPLv3+)
Classifier: Natural Language :: English
Classifier: Operating System :: MacOS :: MacOS X
Classifier: Operating System :: Microsoft :: Windows
Classifier: Operating System :: POSIX
Classifier: Programming Language :: Python :: 2
Classifier: Programming Language :: Python :: 2.7
Classifier: Programming Language :: Python :: 2.6
Classifier: Programming Language :: Python :: 3
Classifier: Programming Language :: Python :: 3.2
Classifier: Programming Language :: Python :: 3.3
Classifier: Programming Language :: Python :: 3.4
Classifier: Programming Language :: Cython
Classifier: Topic :: Education
Classifier: Topic :: Scientific/Engineering :: Electronic Design Automation (EDA)
Requires: scipy (>=0.10.1)
Requires: numpy (>=1.8.0)
Requires: matplotlib (>= 1.1.0)
Requires: cvxopt (>=1.1.4)
Requires: cython (>=0.16)
Requires: setuptools (>=3.3)
Requires: nose (>=1.0)
